{
	"_id": "VoC1nZefkhuUX9Z5",
	"_key": "!items!VoC1nZefkhuUX9Z5",
	"effects": [
		"aqImsK1M1aQUNDC0"
	],
	"folder": null,
	"img": "icons/creatures/abilities/mouth-teeth-long-red.webp",
	"name": "Spell Effect: Vicious Bite",
	"system": {
		"bonuses": {
			"damageMultiplier": "2",
			"weaponDamageExtraDieByProperty": "d6|bite-attack"
		},
		"category": "effect",
		"description": "",
		"duration": {
			"type": "unlimited",
			"value": -1
		},
		"effectPanel": {
			"show": true
		},
		"light": {
			"active": false,
			"hasBeenUsed": false,
			"isSource": false,
			"longevityMins": 60,
			"remainingSecs": 3600,
			"template": "torch"
		},
		"predefinedEffects": "",
		"source": {
			"title": ""
		},
		"start": {
			"combatTime": "11.0",
			"value": 21898
		},
		"tokenIcon": {
			"show": true
		}
	},
	"type": "Effect"
}
